pyrevm-0.3.3.dist-info/METADATA
pyrevm-0.3.3.dist-info/WHEEL
pyrevm/__init__.py
pyrevm/__init__.pyi
pyrevm/py.typed
pyrevm/pyrevm.cpython-312-x86_64-linux-gnu.so
pyrevm-0.3.3.dist-info/RECORD
